twoup/__init__.py
twoup/skeleton.py
twoup-0.2.dist-info/AUTHORS.rst
twoup-0.2.dist-info/LICENSE.txt
twoup-0.2.dist-info/METADATA
twoup-0.2.dist-info/WHEEL
twoup-0.2.dist-info/entry_points.txt
twoup-0.2.dist-info/top_level.txt
twoup-0.2.dist-info/RECORD
