Metadata-Version: 2.1
Name: twoup
Version: 0.2
Summary: List page number sequence to print a small folded double sided booklet
Home-page: http://github.com/m-anish/twoup
Author: Anish Mangal
Author-email: anishmg@umich.edu
License: gpl3
Project-URL: Documentation, http://github.com/m-anish/twoup
Platform: any
Classifier: Development Status :: 4 - Beta
Classifier: Programming Language :: Python
Provides-Extra: testing
Requires-Dist: pytest ; extra == 'testing'
Requires-Dist: pytest-cov ; extra == 'testing'
